scripts/__init__.py
scripts/vantiv_python_sdk_setup.py
vantivecommercesdk-12.48.0.dist-info/licenses/LICENSE
vantivsdk/__init__.py
vantivsdk/batch.py
vantivsdk/batch_txns.py
vantivsdk/commManager.py
vantivsdk/dict2obj.py
vantivsdk/dictmap.py
vantivsdk/fields.py
vantivsdk/online.py
vantivsdk/pgp_helper.py
vantivsdk/utils.py
vantivsdk/version.py
vantivecommercesdk-12.48.0.dist-info/METADATA
vantivecommercesdk-12.48.0.dist-info/WHEEL
vantivecommercesdk-12.48.0.dist-info/entry_points.txt
vantivecommercesdk-12.48.0.dist-info/top_level.txt
vantivecommercesdk-12.48.0.dist-info/RECORD
